systemJSON/__init__.py
systemJSON-0.2.dist-info/METADATA
systemJSON-0.2.dist-info/WHEEL
systemJSON-0.2.dist-info/top_level.txt
systemJSON-0.2.dist-info/RECORD
