Metadata-Version: 2.1
Name: systemJSON
Version: 0.2
Summary: lib for python json
Author: DanXvo
Author-email: coldreality@mail.ru
Classifier: Programming Language :: Python :: 3
Classifier: License :: OSI Approved :: MIT License
Classifier: Operating System :: OS Independent
Requires-Python: >=3.6
